MANIFEST.in
README
setup.py
poppy_ergo_starter/__init__.py
poppy_ergo_starter/_version.py
poppy_ergo_starter/poppy_ergo_starter.py
poppy_ergo_starter.egg-info/PKG-INFO
poppy_ergo_starter.egg-info/SOURCES.txt
poppy_ergo_starter.egg-info/dependency_links.txt
poppy_ergo_starter.egg-info/not-zip-safe
poppy_ergo_starter.egg-info/requires.txt
poppy_ergo_starter.egg-info/top_level.txt
poppy_ergo_starter/configuration/poppy_ergo_starter.json
poppy_ergo_starter/vrep-scene/poppy-ergo-starter.ttt