Metadata-Version: 1.0
Name: poppy-ergo-starter
Version: 2.0.0
Summary:  Poppy Ergo Starter Software Library
Home-page: https://github.com/poppy-project/poppy-ergo-starter
Author: https://github.com/poppy-project/poppy-ergo-starter/graphs/contributors
Author-email: pierre.rouanet@gmail.com
License: GNU GENERAL PUBLIC LICENSE Version 3
Platform: UNKNOWN
